{
  "project_info": {
    "project_number": "706115295900",
    "project_id": "flutter-coding-challenge-a89c8",
    "storage_bucket": "flutter-coding-challenge-a89c8.appspot.com"
  },
  "client": [
    {
      "client_info": {
        "mobilesdk_app_id": "1:706115295900:android:0b69558cc0d3063c98ab59",
        "android_client_info": {
          "package_name": "com.example.flutter_coding_challenge"
        }
      },
      "oauth_client": [
        {
          "client_id": "706115295900-vrp82vsrhfnhrvsam65n4aft8ahefgn8.apps.googleusercontent.com",
          "client_type": 1,
          "android_info": {
            "package_name": "com.example.flutter_coding_challenge",
            "certificate_hash": "5e9a21fefdb66891332ded805232f142eba7c15e"
          }
        },
        {
          "client_id": "706115295900-1mu9po9hp9oiu4fottatrm82o17g6bt7.apps.googleusercontent.com",
          "client_type": 3
        }
      ],
      "api_key": [
        {
          "current_key": "AIzaSyAA6QvuWnBfQ_9KOYK7uQan9a-CeVuJcKg"
        }
      ],
      "services": {
        "appinvite_service": {
          "other_platform_oauth_client": [
            {
              "client_id": "706115295900-1mu9po9hp9oiu4fottatrm82o17g6bt7.apps.googleusercontent.com",
              "client_type": 3
            },
            {
              "client_id": "706115295900-l33cjd5itvmg60t6h9lj3299uegllhkr.apps.googleusercontent.com",
              "client_type": 2,
              "ios_info": {
                "bundle_id": "com.example.flutterCodingChallenge.RunnerTests"
              }
            }
          ]
        }
      }
    }
  ],
  "configuration_version": "1"
}